{
  "project_info": {
    "project_number": "977093574035",
    "firebase_url": "https://accura-261808.firebaseio.com",
    "project_id": "accura-261808",
    "storage_bucket": "accura-261808.appspot.com"
  },
  "client": [
    {
      "client_info": {
        "mobilesdk_app_id": "1:977093574035:android:122d8fe71eaca9fba63c66",
        "android_client_info": {
          "package_name": "com.accurascan.accuraocr.sample"
        }
      },
      "oauth_client": [
        {
          "client_id": "977093574035-31eb9h5kclsocie6vs4k0n5c6lgov3mq.apps.googleusercontent.com",
          "client_type": 3
        }
      ],
      "api_key": [
        {
          "current_key": "AIzaSyARmIHuoT03kaUyNeBHpvGF22pft8pL3_U"
        }
      ],
      "services": {
        "appinvite_service": {
          "other_platform_oauth_client": [
            {
              "client_id": "977093574035-g7cq6fs9squk9tkovbthrdb9m6cocvgk.apps.googleusercontent.com",
              "client_type": 3
            }
          ]
        }
      }
    },
    {
      "client_info": {
        "mobilesdk_app_id": "1:977093574035:android:5bfbb4b0ff6fb817a63c66",
        "android_client_info": {
          "package_name": "com.accurascan.ocr.mrz"
        }
      },
      "oauth_client": [
        {
          "client_id": "977093574035-31eb9h5kclsocie6vs4k0n5c6lgov3mq.apps.googleusercontent.com",
          "client_type": 3
        }
      ],
      "api_key": [
        {
          "current_key": "AIzaSyARmIHuoT03kaUyNeBHpvGF22pft8pL3_U"
        }
      ],
      "services": {
        "appinvite_service": {
          "other_platform_oauth_client": [
            {
              "client_id": "977093574035-g7cq6fs9squk9tkovbthrdb9m6cocvgk.apps.googleusercontent.com",
              "client_type": 3
            }
          ]
        }
      }
    }
  ],
  "configuration_version": "1"
}